star_privateer/__init__.py
star_privateer/aux.py
star_privateer/correlation.py
star_privateer/fliper.py
star_privateer/lomb_scargle.py
star_privateer/morphology.py
star_privateer/rooster.py
star_privateer/rotation_pipeline.py
star_privateer/wavelets.py
star_privateer/catalogs/__init__.py
star_privateer/catalogs/plato-sim.csv
star_privateer/catalogs/santos-19-21.csv
star_privateer/catalogs/santos-21-norot.csv
star_privateer/catalogs/santos_2019_catalog.fit
star_privateer/catalogs/santos_2021_catalog.fit
star_privateer/catalogs/santos_2021_norot.fit
star_privateer/constants/__init__.py
star_privateer/constants/constants.hdf5
star_privateer/rooster_instances/__init__.py
star_privateer/rooster_instances/training_features_gls_only.csv
star_privateer/rooster_instances/training_features_wps_gls.csv
star_privateer/timeseries/003733735.fits
star_privateer/timeseries/008006161.fits
star_privateer/timeseries/010644253.fits
star_privateer/timeseries/__init__.py
star_privateer/timeseries/epic211015853.fits
star_privateer/timeseries/virgo_2_hour_blue.fits
star_privateer/timeseries/virgo_2_hour_green.fits
star_privateer/timeseries/virgo_2_hour_red.fits
star_privateer-1.3.0.dist-info/licenses/LICENSE
star_privateer-1.3.0.dist-info/METADATA
star_privateer-1.3.0.dist-info/WHEEL
star_privateer-1.3.0.dist-info/top_level.txt
star_privateer-1.3.0.dist-info/RECORD
