Metadata-Version: 2.4
Name: star-privateer
Version: 1.3.0
Summary: Module for stellar surface rotation and activity analysis
Author-email: "Sylvain N. Breton" <sylvain.breton@inaf.it>
License: Copyright (C) 2024 Sylvain Breton 
Project-URL: Homepage, https://gitlab.com/sybreton/star_privateer
Project-URL: Documentation, https://star-privateer.readthedocs.io/en/latest/
Keywords: stellar physics,stellar rotation,stellar activity,solar-type stars,light curves
Classifier: Programming Language :: Python :: 3
Classifier: License :: OSI Approved :: CMU License (MIT-CMU)
Classifier: Operating System :: OS Independent
Requires-Python: >=3.7
License-File: LICENSE
Requires-Dist: numpy
Requires-Dist: pandas
Requires-Dist: matplotlib
Requires-Dist: astropy
Requires-Dist: scipy
Requires-Dist: tqdm
Requires-Dist: scikit-learn
Requires-Dist: scikit-image
Requires-Dist: ssqueezepy
Requires-Dist: h5py
Requires-Dist: pycwt
Requires-Dist: pywavelets
Dynamic: license-file
